awusb/__init__.py
awusb/__main__.py
awusb/_version.py
awusb/client.py
awusb/config.py
awusb/models.py
awusb/server.py
awusb/service.py
awusb/usbdevice.py
awusb/utility.py
awusb-1.0.0.dist-info/licenses/LICENSE
awusb-1.0.0.dist-info/METADATA
awusb-1.0.0.dist-info/WHEEL
awusb-1.0.0.dist-info/entry_points.txt
awusb-1.0.0.dist-info/top_level.txt
awusb-1.0.0.dist-info/RECORD
