Metadata-Version: 2.4
Name: awusb
Version: 1.0.0
Summary: a container that mounts remote devices locally using anywhereusb
Author-email: Giles Knap <giles.knap@diamond.ac.uk>
License:                                  Apache License
Project-URL: GitHub, https://github.com/epics-containers/awusb
Classifier: Development Status :: 3 - Alpha
Classifier: License :: OSI Approved :: Apache Software License
Classifier: Programming Language :: Python :: 3.11
Classifier: Programming Language :: Python :: 3.12
Classifier: Programming Language :: Python :: 3.13
Requires-Python: >=3.11
License-File: LICENSE
Requires-Dist: pydantic>=2.0.0
Requires-Dist: pyusb>=1.3.1
Requires-Dist: pyyaml>=6.0.0
Requires-Dist: typer>=0.20.0
Dynamic: license-file
